{
  "timestamp": "market close on December 08, 2025",
  "top_performer": {
    "stock": "WBD",
    "company_name": "Warner Bros. Discovery",
    "wiki_url": "https://en.wikipedia.org/wiki/Warner_Bros._Discovery",
    "change_percent": 4.49,
    "price": 27.23,
    "analysis": "Warner Bros. Discovery's 4.49% surge today was driven by Paramount's unsolicited $30 per share takeover bid (a 139% premium to recent prices), which offers superior value compared to Netflix's existing $27.75 per share deal and creates a bidding war scenario for WBD shareholders. The extremely heavy trading volume (342% of average) and overbought RSI of 89.7 confirm strong investor enthusiasm for the competing offers, with the market pricing in the potential for even higher bids.",
    "article_urls": [
      "https://variety.com/2025/tv/news/warner-bros-discovery-review-paramount-skydance-acquisition-bid-1236603529/",
      "https://abcnews.go.com/Business/paramount-launches-hostile-bid-warner-bros-discovery/story?id=128207805",
      "https://finance.yahoo.com/news/paramount-makes-108-billion-all-cash-offer-for-warner-bros-discovery-escalating-buyout-fight-with-netflix-144453654.html"
    ],
    "historical_data": [
      {
        "date": "2024-12-09",
        "close": 10.57
      },
      {
        "date": "2024-12-10",
        "close": 10.9
      },
      {
        "date": "2024-12-11",
        "close": 10.82
      },
      {
        "date": "2024-12-12",
        "close": 12.49
      },
      {
        "date": "2024-12-13",
        "close": 12.07
      },
      {
        "date": "2024-12-16",
        "close": 11.59
      },
      {
        "date": "2024-12-17",
        "close": 11.34
      },
      {
        "date": "2024-12-18",
        "close": 10.61
      },
      {
        "date": "2024-12-19",
        "close": 10.49
      },
      {
        "date": "2024-12-20",
        "close": 10.71
      },
      {
        "date": "2024-12-23",
        "close": 10.52
      },
      {
        "date": "2024-12-24",
        "close": 10.56
      },
      {
        "date": "2024-12-26",
        "close": 10.62
      },
      {
        "date": "2024-12-27",
        "close": 10.62
      },
      {
        "date": "2024-12-30",
        "close": 10.52
      },
      {
        "date": "2024-12-31",
        "close": 10.58
      },
      {
        "date": "2025-01-02",
        "close": 10.68
      },
      {
        "date": "2025-01-03",
        "close": 10.57
      },
      {
        "date": "2025-01-06",
        "close": 10.83
      },
      {
        "date": "2025-01-07",
        "close": 10.52
      },
      {
        "date": "2025-01-08",
        "close": 10.07
      },
      {
        "date": "2025-01-10",
        "close": 9.7
      },
      {
        "date": "2025-01-13",
        "close": 9.85
      },
      {
        "date": "2025-01-14",
        "close": 9.74
      },
      {
        "date": "2025-01-15",
        "close": 9.8
      },
      {
        "date": "2025-01-16",
        "close": 9.47
      },
      {
        "date": "2025-01-17",
        "close": 9.52
      },
      {
        "date": "2025-01-21",
        "close": 9.77
      },
      {
        "date": "2025-01-22",
        "close": 10.05
      },
      {
        "date": "2025-01-23",
        "close": 10.28
      },
      {
        "date": "2025-01-24",
        "close": 10.26
      },
      {
        "date": "2025-01-27",
        "close": 10.48
      },
      {
        "date": "2025-01-28",
        "close": 10.26
      },
      {
        "date": "2025-01-29",
        "close": 10.41
      },
      {
        "date": "2025-01-30",
        "close": 10.61
      },
      {
        "date": "2025-01-31",
        "close": 10.43
      },
      {
        "date": "2025-02-03",
        "close": 10.17
      },
      {
        "date": "2025-02-04",
        "close": 10.05
      },
      {
        "date": "2025-02-05",
        "close": 10.19
      },
      {
        "date": "2025-02-06",
        "close": 10.21
      },
      {
        "date": "2025-02-07",
        "close": 10.16
      },
      {
        "date": "2025-02-10",
        "close": 9.96
      },
      {
        "date": "2025-02-11",
        "close": 9.85
      },
      {
        "date": "2025-02-12",
        "close": 9.82
      },
      {
        "date": "2025-02-13",
        "close": 10.2
      },
      {
        "date": "2025-02-14",
        "close": 10.34
      },
      {
        "date": "2025-02-18",
        "close": 10.62
      },
      {
        "date": "2025-02-19",
        "close": 10.9
      },
      {
        "date": "2025-02-20",
        "close": 11.06
      },
      {
        "date": "2025-02-21",
        "close": 10.79
      },
      {
        "date": "2025-02-24",
        "close": 11.08
      },
      {
        "date": "2025-02-25",
        "close": 10.7
      },
      {
        "date": "2025-02-26",
        "close": 10.49
      },
      {
        "date": "2025-02-27",
        "close": 10.99
      },
      {
        "date": "2025-02-28",
        "close": 11.47
      },
      {
        "date": "2025-03-03",
        "close": 11.03
      },
      {
        "date": "2025-03-04",
        "close": 11.33
      },
      {
        "date": "2025-03-05",
        "close": 11.44
      },
      {
        "date": "2025-03-06",
        "close": 10.7
      },
      {
        "date": "2025-03-07",
        "close": 11.07
      },
      {
        "date": "2025-03-10",
        "close": 10.59
      },
      {
        "date": "2025-03-11",
        "close": 10.37
      },
      {
        "date": "2025-03-12",
        "close": 10.41
      },
      {
        "date": "2025-03-13",
        "close": 9.9
      },
      {
        "date": "2025-03-14",
        "close": 10.18
      },
      {
        "date": "2025-03-17",
        "close": 10.48
      },
      {
        "date": "2025-03-18",
        "close": 10.39
      },
      {
        "date": "2025-03-19",
        "close": 10.93
      },
      {
        "date": "2025-03-20",
        "close": 10.66
      },
      {
        "date": "2025-03-21",
        "close": 10.74
      },
      {
        "date": "2025-03-24",
        "close": 10.97
      },
      {
        "date": "2025-03-25",
        "close": 10.98
      },
      {
        "date": "2025-03-26",
        "close": 11.04
      },
      {
        "date": "2025-03-27",
        "close": 11.01
      },
      {
        "date": "2025-03-28",
        "close": 10.37
      },
      {
        "date": "2025-03-31",
        "close": 10.72
      },
      {
        "date": "2025-04-01",
        "close": 10.22
      },
      {
        "date": "2025-04-02",
        "close": 10.56
      },
      {
        "date": "2025-04-03",
        "close": 9.16
      },
      {
        "date": "2025-04-04",
        "close": 8.07
      },
      {
        "date": "2025-04-07",
        "close": 8.08
      },
      {
        "date": "2025-04-08",
        "close": 7.71
      },
      {
        "date": "2025-04-09",
        "close": 9.26
      },
      {
        "date": "2025-04-10",
        "close": 8.1
      },
      {
        "date": "2025-04-11",
        "close": 7.96
      },
      {
        "date": "2025-04-14",
        "close": 8.02
      },
      {
        "date": "2025-04-15",
        "close": 8.24
      },
      {
        "date": "2025-04-16",
        "close": 7.95
      },
      {
        "date": "2025-04-17",
        "close": 8.1
      },
      {
        "date": "2025-04-21",
        "close": 7.95
      },
      {
        "date": "2025-04-22",
        "close": 7.96
      },
      {
        "date": "2025-04-23",
        "close": 8.33
      },
      {
        "date": "2025-04-24",
        "close": 8.48
      },
      {
        "date": "2025-04-25",
        "close": 8.57
      },
      {
        "date": "2025-04-28",
        "close": 8.7
      },
      {
        "date": "2025-04-29",
        "close": 8.77
      },
      {
        "date": "2025-04-30",
        "close": 8.65
      },
      {
        "date": "2025-05-01",
        "close": 8.41
      },
      {
        "date": "2025-05-02",
        "close": 8.52
      },
      {
        "date": "2025-05-05",
        "close": 8.37
      },
      {
        "date": "2025-05-06",
        "close": 8.42
      },
      {
        "date": "2025-05-07",
        "close": 8.59
      },
      {
        "date": "2025-05-08",
        "close": 9.0
      },
      {
        "date": "2025-05-09",
        "close": 9.05
      },
      {
        "date": "2025-05-12",
        "close": 9.24
      },
      {
        "date": "2025-05-13",
        "close": 9.2
      },
      {
        "date": "2025-05-14",
        "close": 9.18
      },
      {
        "date": "2025-05-15",
        "close": 9.13
      },
      {
        "date": "2025-05-16",
        "close": 9.15
      },
      {
        "date": "2025-05-19",
        "close": 9.04
      },
      {
        "date": "2025-05-20",
        "close": 9.23
      },
      {
        "date": "2025-05-21",
        "close": 8.96
      },
      {
        "date": "2025-05-22",
        "close": 9.03
      },
      {
        "date": "2025-05-23",
        "close": 9.01
      },
      {
        "date": "2025-05-27",
        "close": 9.55
      },
      {
        "date": "2025-05-28",
        "close": 10.03
      },
      {
        "date": "2025-05-29",
        "close": 10.04
      },
      {
        "date": "2025-05-30",
        "close": 9.96
      },
      {
        "date": "2025-06-02",
        "close": 10.01
      },
      {
        "date": "2025-06-03",
        "close": 9.95
      },
      {
        "date": "2025-06-04",
        "close": 9.79
      },
      {
        "date": "2025-06-05",
        "close": 9.66
      },
      {
        "date": "2025-06-06",
        "close": 9.81
      },
      {
        "date": "2025-06-09",
        "close": 9.54
      },
      {
        "date": "2025-06-10",
        "close": 10.02
      },
      {
        "date": "2025-06-11",
        "close": 10.53
      },
      {
        "date": "2025-06-12",
        "close": 10.17
      },
      {
        "date": "2025-06-13",
        "close": 10.05
      },
      {
        "date": "2025-06-16",
        "close": 10.77
      },
      {
        "date": "2025-06-17",
        "close": 10.59
      },
      {
        "date": "2025-06-18",
        "close": 10.59
      },
      {
        "date": "2025-06-20",
        "close": 10.51
      },
      {
        "date": "2025-06-23",
        "close": 10.66
      },
      {
        "date": "2025-06-24",
        "close": 10.89
      },
      {
        "date": "2025-06-25",
        "close": 10.87
      },
      {
        "date": "2025-06-26",
        "close": 11.14
      },
      {
        "date": "2025-06-27",
        "close": 11.3
      },
      {
        "date": "2025-06-30",
        "close": 11.47
      },
      {
        "date": "2025-07-01",
        "close": 10.95
      },
      {
        "date": "2025-07-02",
        "close": 11.12
      },
      {
        "date": "2025-07-03",
        "close": 11.2
      },
      {
        "date": "2025-07-07",
        "close": 11.02
      },
      {
        "date": "2025-07-08",
        "close": 11.4
      },
      {
        "date": "2025-07-09",
        "close": 11.5
      },
      {
        "date": "2025-07-10",
        "close": 11.64
      },
      {
        "date": "2025-07-11",
        "close": 11.73
      },
      {
        "date": "2025-07-14",
        "close": 11.99
      },
      {
        "date": "2025-07-15",
        "close": 12.02
      },
      {
        "date": "2025-07-16",
        "close": 12.58
      },
      {
        "date": "2025-07-17",
        "close": 12.85
      },
      {
        "date": "2025-07-18",
        "close": 12.74
      },
      {
        "date": "2025-07-21",
        "close": 12.8
      },
      {
        "date": "2025-07-22",
        "close": 12.86
      },
      {
        "date": "2025-07-23",
        "close": 13.31
      },
      {
        "date": "2025-07-24",
        "close": 13.5
      },
      {
        "date": "2025-07-25",
        "close": 13.48
      },
      {
        "date": "2025-07-28",
        "close": 13.68
      },
      {
        "date": "2025-07-29",
        "close": 13.12
      },
      {
        "date": "2025-07-30",
        "close": 13.26
      },
      {
        "date": "2025-07-31",
        "close": 13.17
      },
      {
        "date": "2025-08-01",
        "close": 12.87
      },
      {
        "date": "2025-08-04",
        "close": 12.8
      },
      {
        "date": "2025-08-05",
        "close": 12.73
      },
      {
        "date": "2025-08-06",
        "close": 12.8
      },
      {
        "date": "2025-08-07",
        "close": 11.86
      },
      {
        "date": "2025-08-08",
        "close": 10.9
      },
      {
        "date": "2025-08-11",
        "close": 10.78
      },
      {
        "date": "2025-08-12",
        "close": 11.21
      },
      {
        "date": "2025-08-13",
        "close": 12.04
      },
      {
        "date": "2025-08-14",
        "close": 11.76
      },
      {
        "date": "2025-08-15",
        "close": 11.85
      },
      {
        "date": "2025-08-18",
        "close": 11.81
      },
      {
        "date": "2025-08-19",
        "close": 11.56
      },
      {
        "date": "2025-08-20",
        "close": 11.54
      },
      {
        "date": "2025-08-21",
        "close": 11.59
      },
      {
        "date": "2025-08-22",
        "close": 12.06
      },
      {
        "date": "2025-08-25",
        "close": 12.03
      },
      {
        "date": "2025-08-26",
        "close": 11.8
      },
      {
        "date": "2025-08-27",
        "close": 12.16
      },
      {
        "date": "2025-08-28",
        "close": 12.05
      },
      {
        "date": "2025-08-29",
        "close": 11.63
      },
      {
        "date": "2025-09-02",
        "close": 11.63
      },
      {
        "date": "2025-09-03",
        "close": 11.91
      },
      {
        "date": "2025-09-04",
        "close": 11.77
      },
      {
        "date": "2025-09-05",
        "close": 12.11
      },
      {
        "date": "2025-09-08",
        "close": 12.37
      },
      {
        "date": "2025-09-09",
        "close": 12.27
      },
      {
        "date": "2025-09-10",
        "close": 12.55
      },
      {
        "date": "2025-09-11",
        "close": 16.17
      },
      {
        "date": "2025-09-12",
        "close": 18.87
      },
      {
        "date": "2025-09-15",
        "close": 19.5
      },
      {
        "date": "2025-09-16",
        "close": 18.24
      },
      {
        "date": "2025-09-17",
        "close": 18.01
      },
      {
        "date": "2025-09-18",
        "close": 18.7
      },
      {
        "date": "2025-09-19",
        "close": 19.33
      },
      {
        "date": "2025-09-22",
        "close": 19.62
      },
      {
        "date": "2025-09-23",
        "close": 19.56
      },
      {
        "date": "2025-09-24",
        "close": 19.82
      },
      {
        "date": "2025-09-25",
        "close": 19.77
      },
      {
        "date": "2025-09-26",
        "close": 19.5
      },
      {
        "date": "2025-09-29",
        "close": 18.86
      },
      {
        "date": "2025-09-30",
        "close": 19.52
      },
      {
        "date": "2025-10-01",
        "close": 19.33
      },
      {
        "date": "2025-10-02",
        "close": 19.25
      },
      {
        "date": "2025-10-03",
        "close": 19.0
      },
      {
        "date": "2025-10-06",
        "close": 19.09
      },
      {
        "date": "2025-10-07",
        "close": 18.6
      },
      {
        "date": "2025-10-08",
        "close": 17.89
      },
      {
        "date": "2025-10-09",
        "close": 17.68
      },
      {
        "date": "2025-10-10",
        "close": 17.11
      },
      {
        "date": "2025-10-13",
        "close": 17.76
      },
      {
        "date": "2025-10-14",
        "close": 17.99
      },
      {
        "date": "2025-10-15",
        "close": 18.47
      },
      {
        "date": "2025-10-16",
        "close": 18.3
      },
      {
        "date": "2025-10-17",
        "close": 18.18
      },
      {
        "date": "2025-10-20",
        "close": 18.3
      },
      {
        "date": "2025-10-21",
        "close": 20.34
      },
      {
        "date": "2025-10-22",
        "close": 20.53
      },
      {
        "date": "2025-10-23",
        "close": 21.23
      },
      {
        "date": "2025-10-24",
        "close": 21.14
      },
      {
        "date": "2025-10-27",
        "close": 21.05
      },
      {
        "date": "2025-10-28",
        "close": 20.99
      },
      {
        "date": "2025-10-29",
        "close": 21.34
      },
      {
        "date": "2025-10-30",
        "close": 21.63
      },
      {
        "date": "2025-10-31",
        "close": 22.43
      },
      {
        "date": "2025-11-03",
        "close": 22.28
      },
      {
        "date": "2025-11-04",
        "close": 22.62
      },
      {
        "date": "2025-11-05",
        "close": 22.71
      },
      {
        "date": "2025-11-06",
        "close": 22.44
      },
      {
        "date": "2025-11-07",
        "close": 22.67
      },
      {
        "date": "2025-11-10",
        "close": 22.96
      },
      {
        "date": "2025-11-11",
        "close": 23.08
      },
      {
        "date": "2025-11-12",
        "close": 22.2
      },
      {
        "date": "2025-11-13",
        "close": 22.16
      },
      {
        "date": "2025-11-14",
        "close": 23.02
      },
      {
        "date": "2025-11-17",
        "close": 22.75
      },
      {
        "date": "2025-11-18",
        "close": 23.69
      },
      {
        "date": "2025-11-19",
        "close": 23.08
      },
      {
        "date": "2025-11-20",
        "close": 22.88
      },
      {
        "date": "2025-11-21",
        "close": 23.19
      },
      {
        "date": "2025-11-24",
        "close": 22.86
      },
      {
        "date": "2025-11-25",
        "close": 22.94
      },
      {
        "date": "2025-11-26",
        "close": 23.87
      },
      {
        "date": "2025-11-28",
        "close": 24.02
      },
      {
        "date": "2025-12-01",
        "close": 23.86
      },
      {
        "date": "2025-12-02",
        "close": 24.53
      },
      {
        "date": "2025-12-03",
        "close": 24.59
      },
      {
        "date": "2025-12-04",
        "close": 24.55
      },
      {
        "date": "2025-12-05",
        "close": 26.06
      },
      {
        "date": "2025-12-08",
        "close": 27.23
      }
    ]
  },
  "bottom_performer": {
    "stock": "APD",
    "company_name": "Air Products",
    "wiki_url": "https://en.wikipedia.org/wiki/Air_Products",
    "change_percent": -9.45,
    "price": 236.04,
    "analysis": "Air Products' 9.45% decline appears to be driven by investor concerns over the massive $8-9 billion capital commitment required for the Louisiana Clean Energy Complex, with final investment decisions not expected until 2026 and project completion pushed to 2030, creating uncertainty about returns on this substantial investment. The extremely heavy trading volume (460% of average) and oversold RSI of 23.18 suggest significant selling pressure as investors reassess the company's capital allocation strategy and long-term project timeline risks.",
    "article_urls": [
      "https://www.benzinga.com/markets/equities/25/12/49264950/air-products-stock-drops-as-talks-with-yara-continue"
    ],
    "historical_data": [
      {
        "date": "2024-12-09",
        "close": 308.74
      },
      {
        "date": "2024-12-10",
        "close": 307.37
      },
      {
        "date": "2024-12-11",
        "close": 304.61
      },
      {
        "date": "2024-12-12",
        "close": 303.1
      },
      {
        "date": "2024-12-13",
        "close": 304.54
      },
      {
        "date": "2024-12-16",
        "close": 299.05
      },
      {
        "date": "2024-12-17",
        "close": 296.98
      },
      {
        "date": "2024-12-18",
        "close": 287.93
      },
      {
        "date": "2024-12-19",
        "close": 285.94
      },
      {
        "date": "2024-12-20",
        "close": 286.93
      },
      {
        "date": "2024-12-23",
        "close": 284.95
      },
      {
        "date": "2024-12-24",
        "close": 288.26
      },
      {
        "date": "2024-12-26",
        "close": 287.78
      },
      {
        "date": "2024-12-27",
        "close": 285.52
      },
      {
        "date": "2024-12-30",
        "close": 281.48
      },
      {
        "date": "2024-12-31",
        "close": 282.94
      },
      {
        "date": "2025-01-02",
        "close": 277.9
      },
      {
        "date": "2025-01-03",
        "close": 278.59
      },
      {
        "date": "2025-01-06",
        "close": 277.76
      },
      {
        "date": "2025-01-07",
        "close": 280.86
      },
      {
        "date": "2025-01-08",
        "close": 279.87
      },
      {
        "date": "2025-01-10",
        "close": 287.67
      },
      {
        "date": "2025-01-13",
        "close": 296.2
      },
      {
        "date": "2025-01-14",
        "close": 302.16
      },
      {
        "date": "2025-01-15",
        "close": 301.19
      },
      {
        "date": "2025-01-16",
        "close": 306.14
      },
      {
        "date": "2025-01-17",
        "close": 311.49
      },
      {
        "date": "2025-01-21",
        "close": 313.54
      },
      {
        "date": "2025-01-22",
        "close": 311.01
      },
      {
        "date": "2025-01-23",
        "close": 317.88
      },
      {
        "date": "2025-01-24",
        "close": 322.75
      },
      {
        "date": "2025-01-27",
        "close": 320.61
      },
      {
        "date": "2025-01-28",
        "close": 320.84
      },
      {
        "date": "2025-01-29",
        "close": 321.17
      },
      {
        "date": "2025-01-30",
        "close": 328.91
      },
      {
        "date": "2025-01-31",
        "close": 328.71
      },
      {
        "date": "2025-02-03",
        "close": 331.83
      },
      {
        "date": "2025-02-04",
        "close": 329.2
      },
      {
        "date": "2025-02-05",
        "close": 326.92
      },
      {
        "date": "2025-02-06",
        "close": 322.01
      },
      {
        "date": "2025-02-07",
        "close": 304.91
      },
      {
        "date": "2025-02-10",
        "close": 304.81
      },
      {
        "date": "2025-02-11",
        "close": 303.7
      },
      {
        "date": "2025-02-12",
        "close": 304.57
      },
      {
        "date": "2025-02-13",
        "close": 309.4
      },
      {
        "date": "2025-02-14",
        "close": 310.65
      },
      {
        "date": "2025-02-18",
        "close": 311.09
      },
      {
        "date": "2025-02-19",
        "close": 311.16
      },
      {
        "date": "2025-02-20",
        "close": 308.38
      },
      {
        "date": "2025-02-21",
        "close": 304.1
      },
      {
        "date": "2025-02-24",
        "close": 303.61
      },
      {
        "date": "2025-02-25",
        "close": 311.47
      },
      {
        "date": "2025-02-26",
        "close": 307.9
      },
      {
        "date": "2025-02-27",
        "close": 306.62
      },
      {
        "date": "2025-02-28",
        "close": 310.2
      },
      {
        "date": "2025-03-03",
        "close": 304.5
      },
      {
        "date": "2025-03-04",
        "close": 299.24
      },
      {
        "date": "2025-03-05",
        "close": 305.68
      },
      {
        "date": "2025-03-06",
        "close": 304.68
      },
      {
        "date": "2025-03-07",
        "close": 310.42
      },
      {
        "date": "2025-03-10",
        "close": 297.41
      },
      {
        "date": "2025-03-11",
        "close": 292.44
      },
      {
        "date": "2025-03-12",
        "close": 289.27
      },
      {
        "date": "2025-03-13",
        "close": 287.44
      },
      {
        "date": "2025-03-14",
        "close": 286.44
      },
      {
        "date": "2025-03-17",
        "close": 290.22
      },
      {
        "date": "2025-03-18",
        "close": 286.3
      },
      {
        "date": "2025-03-19",
        "close": 288.61
      },
      {
        "date": "2025-03-20",
        "close": 287.42
      },
      {
        "date": "2025-03-21",
        "close": 285.96
      },
      {
        "date": "2025-03-24",
        "close": 288.17
      },
      {
        "date": "2025-03-25",
        "close": 287.94
      },
      {
        "date": "2025-03-26",
        "close": 289.59
      },
      {
        "date": "2025-03-27",
        "close": 289.41
      },
      {
        "date": "2025-03-28",
        "close": 286.83
      },
      {
        "date": "2025-03-31",
        "close": 289.13
      },
      {
        "date": "2025-04-01",
        "close": 289.55
      },
      {
        "date": "2025-04-02",
        "close": 291.26
      },
      {
        "date": "2025-04-03",
        "close": 279.22
      },
      {
        "date": "2025-04-04",
        "close": 259.91
      },
      {
        "date": "2025-04-07",
        "close": 255.75
      },
      {
        "date": "2025-04-08",
        "close": 245.44
      },
      {
        "date": "2025-04-09",
        "close": 266.71
      },
      {
        "date": "2025-04-10",
        "close": 258.65
      },
      {
        "date": "2025-04-11",
        "close": 265.42
      },
      {
        "date": "2025-04-14",
        "close": 269.03
      },
      {
        "date": "2025-04-15",
        "close": 262.42
      },
      {
        "date": "2025-04-16",
        "close": 257.89
      },
      {
        "date": "2025-04-17",
        "close": 259.62
      },
      {
        "date": "2025-04-21",
        "close": 254.25
      },
      {
        "date": "2025-04-22",
        "close": 262.1
      },
      {
        "date": "2025-04-23",
        "close": 261.47
      },
      {
        "date": "2025-04-24",
        "close": 265.41
      },
      {
        "date": "2025-04-25",
        "close": 264.12
      },
      {
        "date": "2025-04-28",
        "close": 265.88
      },
      {
        "date": "2025-04-29",
        "close": 267.36
      },
      {
        "date": "2025-04-30",
        "close": 267.84
      },
      {
        "date": "2025-05-01",
        "close": 268.63
      },
      {
        "date": "2025-05-02",
        "close": 273.98
      },
      {
        "date": "2025-05-05",
        "close": 268.63
      },
      {
        "date": "2025-05-06",
        "close": 264.16
      },
      {
        "date": "2025-05-07",
        "close": 261.27
      },
      {
        "date": "2025-05-08",
        "close": 266.34
      },
      {
        "date": "2025-05-09",
        "close": 267.59
      },
      {
        "date": "2025-05-12",
        "close": 272.45
      },
      {
        "date": "2025-05-13",
        "close": 270.28
      },
      {
        "date": "2025-05-14",
        "close": 267.99
      },
      {
        "date": "2025-05-15",
        "close": 271.01
      },
      {
        "date": "2025-05-16",
        "close": 275.35
      },
      {
        "date": "2025-05-19",
        "close": 273.79
      },
      {
        "date": "2025-05-20",
        "close": 272.41
      },
      {
        "date": "2025-05-21",
        "close": 266.47
      },
      {
        "date": "2025-05-22",
        "close": 265.66
      },
      {
        "date": "2025-05-23",
        "close": 266.51
      },
      {
        "date": "2025-05-27",
        "close": 271.04
      },
      {
        "date": "2025-05-28",
        "close": 268.44
      },
      {
        "date": "2025-05-29",
        "close": 269.53
      },
      {
        "date": "2025-05-30",
        "close": 275.32
      },
      {
        "date": "2025-06-02",
        "close": 275.06
      },
      {
        "date": "2025-06-03",
        "close": 279.64
      },
      {
        "date": "2025-06-04",
        "close": 276.75
      },
      {
        "date": "2025-06-05",
        "close": 272.85
      },
      {
        "date": "2025-06-06",
        "close": 276.29
      },
      {
        "date": "2025-06-09",
        "close": 276.37
      },
      {
        "date": "2025-06-10",
        "close": 278.42
      },
      {
        "date": "2025-06-11",
        "close": 278.7
      },
      {
        "date": "2025-06-12",
        "close": 279.49
      },
      {
        "date": "2025-06-13",
        "close": 276.67
      },
      {
        "date": "2025-06-16",
        "close": 276.94
      },
      {
        "date": "2025-06-17",
        "close": 273.63
      },
      {
        "date": "2025-06-18",
        "close": 271.73
      },
      {
        "date": "2025-06-20",
        "close": 267.1
      },
      {
        "date": "2025-06-23",
        "close": 269.63
      },
      {
        "date": "2025-06-24",
        "close": 277.14
      },
      {
        "date": "2025-06-25",
        "close": 278.43
      },
      {
        "date": "2025-06-26",
        "close": 279.38
      },
      {
        "date": "2025-06-27",
        "close": 278.8
      },
      {
        "date": "2025-06-30",
        "close": 278.41
      },
      {
        "date": "2025-07-01",
        "close": 283.62
      },
      {
        "date": "2025-07-02",
        "close": 288.42
      },
      {
        "date": "2025-07-03",
        "close": 290.04
      },
      {
        "date": "2025-07-07",
        "close": 287.13
      },
      {
        "date": "2025-07-08",
        "close": 290.47
      },
      {
        "date": "2025-07-09",
        "close": 292.27
      },
      {
        "date": "2025-07-10",
        "close": 292.22
      },
      {
        "date": "2025-07-11",
        "close": 290.12
      },
      {
        "date": "2025-07-14",
        "close": 289.15
      },
      {
        "date": "2025-07-15",
        "close": 284.83
      },
      {
        "date": "2025-07-16",
        "close": 287.19
      },
      {
        "date": "2025-07-17",
        "close": 291.65
      },
      {
        "date": "2025-07-18",
        "close": 293.35
      },
      {
        "date": "2025-07-21",
        "close": 292.19
      },
      {
        "date": "2025-07-22",
        "close": 296.17
      },
      {
        "date": "2025-07-23",
        "close": 295.85
      },
      {
        "date": "2025-07-24",
        "close": 295.66
      },
      {
        "date": "2025-07-25",
        "close": 297.27
      },
      {
        "date": "2025-07-28",
        "close": 293.46
      },
      {
        "date": "2025-07-29",
        "close": 293.36
      },
      {
        "date": "2025-07-30",
        "close": 288.52
      },
      {
        "date": "2025-07-31",
        "close": 285.99
      },
      {
        "date": "2025-08-01",
        "close": 279.96
      },
      {
        "date": "2025-08-04",
        "close": 285.24
      },
      {
        "date": "2025-08-05",
        "close": 290.65
      },
      {
        "date": "2025-08-06",
        "close": 287.14
      },
      {
        "date": "2025-08-07",
        "close": 286.62
      },
      {
        "date": "2025-08-08",
        "close": 286.71
      },
      {
        "date": "2025-08-11",
        "close": 282.15
      },
      {
        "date": "2025-08-12",
        "close": 287.44
      },
      {
        "date": "2025-08-13",
        "close": 292.19
      },
      {
        "date": "2025-08-14",
        "close": 290.01
      },
      {
        "date": "2025-08-15",
        "close": 288.45
      },
      {
        "date": "2025-08-18",
        "close": 286.34
      },
      {
        "date": "2025-08-19",
        "close": 288.3
      },
      {
        "date": "2025-08-20",
        "close": 290.53
      },
      {
        "date": "2025-08-21",
        "close": 291.51
      },
      {
        "date": "2025-08-22",
        "close": 297.24
      },
      {
        "date": "2025-08-25",
        "close": 292.41
      },
      {
        "date": "2025-08-26",
        "close": 292.11
      },
      {
        "date": "2025-08-27",
        "close": 292.97
      },
      {
        "date": "2025-08-28",
        "close": 292.96
      },
      {
        "date": "2025-08-29",
        "close": 291.98
      },
      {
        "date": "2025-09-02",
        "close": 290.32
      },
      {
        "date": "2025-09-03",
        "close": 289.31
      },
      {
        "date": "2025-09-04",
        "close": 288.03
      },
      {
        "date": "2025-09-05",
        "close": 287.63
      },
      {
        "date": "2025-09-08",
        "close": 286.91
      },
      {
        "date": "2025-09-09",
        "close": 285.24
      },
      {
        "date": "2025-09-10",
        "close": 285.53
      },
      {
        "date": "2025-09-11",
        "close": 292.68
      },
      {
        "date": "2025-09-12",
        "close": 290.93
      },
      {
        "date": "2025-09-15",
        "close": 287.87
      },
      {
        "date": "2025-09-16",
        "close": 283.17
      },
      {
        "date": "2025-09-17",
        "close": 288.66
      },
      {
        "date": "2025-09-18",
        "close": 290.6
      },
      {
        "date": "2025-09-19",
        "close": 288.35
      },
      {
        "date": "2025-09-22",
        "close": 285.62
      },
      {
        "date": "2025-09-23",
        "close": 274.54
      },
      {
        "date": "2025-09-24",
        "close": 270.53
      },
      {
        "date": "2025-09-25",
        "close": 263.86
      },
      {
        "date": "2025-09-26",
        "close": 264.72
      },
      {
        "date": "2025-09-29",
        "close": 268.69
      },
      {
        "date": "2025-09-30",
        "close": 270.98
      },
      {
        "date": "2025-10-01",
        "close": 268.66
      },
      {
        "date": "2025-10-02",
        "close": 270.48
      },
      {
        "date": "2025-10-03",
        "close": 271.4
      },
      {
        "date": "2025-10-06",
        "close": 271.15
      },
      {
        "date": "2025-10-07",
        "close": 270.77
      },
      {
        "date": "2025-10-08",
        "close": 268.7
      },
      {
        "date": "2025-10-09",
        "close": 262.63
      },
      {
        "date": "2025-10-10",
        "close": 257.09
      },
      {
        "date": "2025-10-13",
        "close": 260.78
      },
      {
        "date": "2025-10-14",
        "close": 261.73
      },
      {
        "date": "2025-10-15",
        "close": 257.54
      },
      {
        "date": "2025-10-16",
        "close": 253.0
      },
      {
        "date": "2025-10-17",
        "close": 253.33
      },
      {
        "date": "2025-10-20",
        "close": 254.15
      },
      {
        "date": "2025-10-21",
        "close": 254.78
      },
      {
        "date": "2025-10-22",
        "close": 253.06
      },
      {
        "date": "2025-10-23",
        "close": 255.05
      },
      {
        "date": "2025-10-24",
        "close": 254.98
      },
      {
        "date": "2025-10-27",
        "close": 255.76
      },
      {
        "date": "2025-10-28",
        "close": 254.67
      },
      {
        "date": "2025-10-29",
        "close": 248.22
      },
      {
        "date": "2025-10-30",
        "close": 244.61
      },
      {
        "date": "2025-10-31",
        "close": 242.55
      },
      {
        "date": "2025-11-03",
        "close": 239.39
      },
      {
        "date": "2025-11-04",
        "close": 240.74
      },
      {
        "date": "2025-11-05",
        "close": 237.4
      },
      {
        "date": "2025-11-06",
        "close": 258.8
      },
      {
        "date": "2025-11-07",
        "close": 259.64
      },
      {
        "date": "2025-11-10",
        "close": 258.31
      },
      {
        "date": "2025-11-11",
        "close": 262.21
      },
      {
        "date": "2025-11-12",
        "close": 261.56
      },
      {
        "date": "2025-11-13",
        "close": 263.06
      },
      {
        "date": "2025-11-14",
        "close": 259.37
      },
      {
        "date": "2025-11-17",
        "close": 253.08
      },
      {
        "date": "2025-11-18",
        "close": 252.12
      },
      {
        "date": "2025-11-19",
        "close": 253.2
      },
      {
        "date": "2025-11-20",
        "close": 251.09
      },
      {
        "date": "2025-11-21",
        "close": 257.46
      },
      {
        "date": "2025-11-24",
        "close": 256.48
      },
      {
        "date": "2025-11-25",
        "close": 258.91
      },
      {
        "date": "2025-11-26",
        "close": 258.96
      },
      {
        "date": "2025-11-28",
        "close": 260.89
      },
      {
        "date": "2025-12-01",
        "close": 260.88
      },
      {
        "date": "2025-12-02",
        "close": 256.8
      },
      {
        "date": "2025-12-03",
        "close": 260.34
      },
      {
        "date": "2025-12-04",
        "close": 261.64
      },
      {
        "date": "2025-12-05",
        "close": 260.69
      },
      {
        "date": "2025-12-08",
        "close": 236.04
      }
    ]
  }
}